{
  "required": true,
  "minVersion": "0.8",
  "package": "dev.engine_room.flywheel.impl.mixin",
  "compatibilityLevel": "JAVA_17",
  "refmap": "flywheel.refmap.json",
  "client": [
    "BlockEntityTypeMixin",
    "ClientChunkCacheMixin",
    "EntityTypeMixin",
    "LevelMixin",
    "LevelRendererMixin",
    "MinecraftMixin",
    "ModelPartAccessor",
    "PoseStackAccessor",
    "PoseStackMixin",
    "fix.FixFabulousDepthMixin",
    "fix.FixNormalScalingMixin",
    "text.BakedGlyphMixin",
    "text.CodePointMapMixin",
    "text.FontAccessor",
    "text.FontSetMixin",
    "text.FontTexture$NodeAccessor",
    "text.FontTextureMixin",
    "visualmanage.BlockEntityMixin",
    "visualmanage.LevelChunkMixin",
    "visualmanage.LevelRendererMixin",
    "visualmanage.RebuildTaskMixin"
  ],
  "injectors": {
    "defaultRequire": 1
  }
}
